{
	"$schema": "https://schemas.wp.org/trunk/theme.json",
	"version": 2,
	"title": "🐼 Panda",
	"settings": {
		"color": {
			"palette": [
				{
					"color": "#BABABA",
					"name": "Primary",
					"slug": "primary"
				},
				{
					"color": "#BABABA",
					"name": "Mono 2",
					"slug": "mono-2"
				},
				{
					"color": "#000000",
					"name": "Contrast Light",
					"slug": "contrast-light"
				},
				{
					"color": "#FFFFFF",
					"name": "Contrast Dark",
					"slug": "contrast-dark"
				},
				{
					"color": "#B5B5B5",
					"name": "Featured",
					"slug": "featured"
				},
				{
					"color": "#171717",
					"name": "Base",
					"slug": "base"
				},
				{
					"color": "#FAFAFA",
					"name": "Mono 1",
					"slug": "mono-1"
				},
				{
					"color": "#3A3A3A",
					"name": "Mono 3",
					"slug": "mono-3"
				},
				{
					"color": "#1E1E1E",
					"name": "Mono 4",
					"slug": "mono-4"
				},
				{
					"color": "#E11D48",
					"name": "Primary Hover",
					"slug": "primary-hover"
				}
			]
		}
	}
}
